vasp_tools/__init__.py
vasp_tools/objects.py
vasp_tools/vector_algebra.py
vasp_tools/vparser.py
vasp_tools-0.1.0.data/scripts/cart-direct.py
vasp_tools-0.1.0.data/scripts/e-gap.py
vasp_tools-0.1.0.data/scripts/e-plot.py
vasp_tools-0.1.0.data/scripts/fix-upto.py
vasp_tools-0.1.0.data/scripts/forces.py
vasp_tools-0.1.0.data/scripts/place-at.py
vasp_tools-0.1.0.data/scripts/rotate.py
vasp_tools-0.1.0.data/scripts/split-by.py
vasp_tools-0.1.0.dist-info/AUTHORS.rst
vasp_tools-0.1.0.dist-info/LICENSE
vasp_tools-0.1.0.dist-info/METADATA
vasp_tools-0.1.0.dist-info/WHEEL
vasp_tools-0.1.0.dist-info/entry_points.txt
vasp_tools-0.1.0.dist-info/top_level.txt
vasp_tools-0.1.0.dist-info/RECORD
