Metadata-Version: 2.1
Name: vasp-tools
Version: 0.1.0
Summary: A suite of scripts that perform menial, tedious and repetitive tasks and operations on VASP files that were hurriedly and haphazardly put together by some intern.
Home-page: https://github.com/RexGalilae/vasp_tools
Author: Zaid Hassan aka RexGalilae
Author-email: mdzaidgr8@gmail.com
License: MIT license
Keywords: vasp python computation dft
Platform: UNKNOWN
Classifier: Development Status :: 2 - Pre-Alpha
Classifier: Intended Audience :: Developers
Classifier: License :: OSI Approved :: MIT License
Classifier: Natural Language :: English
Classifier: Programming Language :: Python :: 2
Classifier: Programming Language :: Python :: 2.6
Classifier: Programming Language :: Python :: 2.7
Classifier: Programming Language :: Python :: 3
Classifier: Programming Language :: Python :: 3.3
Classifier: Programming Language :: Python :: 3.4
Classifier: Programming Language :: Python :: 3.5
Classifier: Programming Language :: Python :: 3.6
Classifier: Programming Language :: Python :: 3.7
Requires-Dist: Cython (==0.29.2)
Requires-Dist: tabulate (==0.8.3)
Requires-Dist: lxml (==4.2.5)
Requires-Dist: mpmath (==1.1.0)
Requires-Dist: numpy (==1.16.4)
Requires-Dist: matplotlib (==3.0.2)
Requires-Dist: sympy (==1.4)
Requires-Dist: cryptography (==2.7)
Requires-Dist: seaborn (==0.9.0)
Requires-Dist: pyOpenSSL (==19.0.0)
Requires-Dist: brotli (==1.0.7)
Requires-Dist: protobuf (==3.9.0)
Requires-Dist: ipaddr (==2.2.0)
Requires-Dist: mock (==3.0.5)
Requires-Dist: ordereddict (==1.1)
Requires-Dist: simplejson (==3.16.0)
Requires-Dist: usercustomize (==1.0.0)
Requires-Dist: wincertstore (==0.2)
Requires-Dist: PyYAML (==5.1.1)
